mupa_server/__init__.py
mupa_server/__main__.py
mupa_server/server.py
mupa_server-0.1.0.dist-info/WHEEL
mupa_server-0.1.0.dist-info/METADATA
mupa_server-0.1.0.dist-info/RECORD
