Metadata-Version: 2.1
Name: mupa-server
Version: 0.1.0
Summary: 
Author: Your Name
Author-email: you@example.com
Requires-Python: >=3.10,<4.0
Classifier: Programming Language :: Python :: 3
Classifier: Programming Language :: Python :: 3.10
Requires-Dist: click (>=8.1.3,<9.0.0)
Requires-Dist: numpy (>=1.23.1,<2.0.0)
Requires-Dist: sounddevice (>=0.4.4,<0.5.0)
